laspated/__init__.py
laspated/add_regressors.py
laspated/data_agg.py
laspated/geo_discretization_utils.py
laspated/h3_utils.py
laspated/squares.py
laspated/time_discretization_utils.py
laspated-0.1.0.dist-info/LICENSE.txt
laspated-0.1.0.dist-info/METADATA
laspated-0.1.0.dist-info/WHEEL
laspated-0.1.0.dist-info/top_level.txt
laspated-0.1.0.dist-info/RECORD
