Metadata-Version: 2.1
Name: laspated
Version: 0.1.0
Summary: Spatio-temporal discrete data analysis
Author: Vincent Guigues, Giovanni Amorim, André Mazal, Victor Nascimento
Keywords: data,analysis,temporal,discrete,geographical
Classifier: Programming Language :: Python :: 3
Classifier: License :: OSI Approved :: MIT License
Classifier: Operating System :: OS Independent
Requires-Python: >=3.6
License-File: LICENSE.txt
Requires-Dist: numpy >=1.20
Requires-Dist: pandas ==2.0.0
Requires-Dist: geopandas ==0.12.2
Requires-Dist: matplotlib
Requires-Dist: h3
Requires-Dist: geovoronoi
Requires-Dist: rtree
Requires-Dist: descartes
